{"Meta Data": {"1. Information": "Daily Prices (open, high, low, close) and Volumes", "2. Symbol": "LEN", "3. Last Refreshed": "2020-04-21 12:11:00", "4. Output Size": "Compact", "5. Time Zone": "US/Eastern"}, "Time Series (Daily)": {"2020-04-21": {"1. open": "39.0000", "2. high": "40.4600", "3. low": "38.5100", "4. close": "39.6500", "5. volume": "1146409"}, "2020-04-20": {"1. open": "41.3800", "2. high": "41.7400", "3. low": "39.5700", "4. close": "39.9800", "5. volume": "2921567"}, "2020-04-17": {"1. open": "43.4800", "2. high": "44.2500", "3. low": "41.6700", "4. close": "42.9300", "5. volume": "3595476"}, "2020-04-16": {"1. open": "40.5000", "2. high": "41.1500", "3. low": "39.5300", "4. close": "40.9000", "5. volume": "3685462"}, "2020-04-15": {"1. open": "41.0000", "2. high": "41.2350", "3. low": "39.2100", "4. close": "39.8200", "5. volume": "3123848"}, "2020-04-14": {"1. open": "43.6400", "2. high": "44.0200", "3. low": "42.2100", "4. close": "43.0200", "5. volume": "2833472"}, "2020-04-13": {"1. open": "44.1500", "2. high": "44.1500", "3. low": "40.8400", "4. close": "41.3500", "5. volume": "3543956"}, "2020-04-09": {"1. open": "45.1000", "2. high": "47.8300", "3. low": "44.0000", "4. close": "44.8000", "5. volume": "5443437"}, "2020-04-08": {"1. open": "40.1400", "2. high": "43.7500", "3. low": "39.5600", "4. close": "43.3600", "5. volume": "4175110"}, "2020-04-07": {"1. open": "42.0000", "2. high": "42.9400", "3. low": "39.0600", "4. close": "39.2600", "5. volume": "4408519"}, "2020-04-06": {"1. open": "36.4600", "2. high": "39.7100", "3. low": "35.6900", "4. close": "39.2200", "5. volume": "4667020"}, "2020-04-03": {"1. open": "33.4200", "2. high": "33.8700", "3. low": "32.4100", "4. close": "33.3900", "5. volume": "3220478"}, "2020-04-02": {"1. open": "34.1400", "2. high": "35.5300", "3. low": "32.4100", "4. close": "33.4200", "5. volume": "4270121"}, "2020-04-01": {"1. open": "36.3300", "2. high": "37.0700", "3. low": "34.4100", "4. close": "34.7300", "5. volume": "4092262"}, "2020-03-31": {"1. open": "40.3700", "2. high": "40.4400", "3. low": "37.6600", "4. close": "38.2000", "5. volume": "4588205"}, "2020-03-30": {"1. open": "40.5500", "2. high": "40.7000", "3. low": "38.0700", "4. close": "39.9600", "5. volume": "3708850"}, "2020-03-27": {"1. open": "40.3400", "2. high": "42.2200", "3. low": "39.2200", "4. close": "40.2600", "5. volume": "4112366"}, "2020-03-26": {"1. open": "41.7500", "2. high": "42.8700", "3. low": "40.3200", "4. close": "42.4200", "5. volume": "4935526"}, "2020-03-25": {"1. open": "36.5200", "2. high": "41.9400", "3. low": "35.5000", "4. close": "40.7100", "5. volume": "6022674"}, "2020-03-24": {"1. open": "32.4500", "2. high": "35.7900", "3. low": "31.1800", "4. close": "35.6000", "5. volume": "5749471"}, "2020-03-23": {"1. open": "31.7500", "2. high": "32.7700", "3. low": "28.2100", "4. close": "29.3500", "5. volume": "7285473"}, "2020-03-20": {"1. open": "32.2600", "2. high": "35.0900", "3. low": "30.2700", "4. close": "34.0800", "5. volume": "8359842"}, "2020-03-19": {"1. open": "29.9900", "2. high": "35.5000", "3. low": "28.8850", "4. close": "31.6100", "5. volume": "8409744"}, "2020-03-18": {"1. open": "32.2100", "2. high": "32.3800", "3. low": "25.4200", "4. close": "30.9200", "5. volume": "8607566"}, "2020-03-17": {"1. open": "37.1900", "2. high": "37.6600", "3. low": "31.7600", "4. close": "34.9700", "5. volume": "8049224"}, "2020-03-16": {"1. open": "39.1000", "2. high": "40.0000", "3. low": "36.4800", "4. close": "36.7200", "5. volume": "9004981"}, "2020-03-13": {"1. open": "49.3400", "2. high": "49.5400", "3. low": "42.1700", "4. close": "45.6800", "5. volume": "6875041"}, "2020-03-12": {"1. open": "50.0000", "2. high": "50.0200", "3. low": "43.7400", "4. close": "46.4200", "5. volume": "7552463"}, "2020-03-11": {"1. open": "57.0600", "2. high": "57.8300", "3. low": "53.3800", "4. close": "53.4100", "5. volume": "4743886"}, "2020-03-10": {"1. open": "57.7700", "2. high": "59.5300", "3. low": "55.0800", "4. close": "59.3500", "5. volume": "4895891"}, "2020-03-09": {"1. open": "58.1900", "2. high": "58.4400", "3. low": "55.3500", "4. close": "55.3500", "5. volume": "5491077"}, "2020-03-06": {"1. open": "62.4600", "2. high": "63.7900", "3. low": "61.0000", "4. close": "62.5500", "5. volume": "4216533"}, "2020-03-05": {"1. open": "65.1800", "2. high": "66.4100", "3. low": "64.4700", "4. close": "64.7000", "5. volume": "3075206"}, "2020-03-04": {"1. open": "65.2700", "2. high": "67.1200", "3. low": "64.3700", "4. close": "66.6400", "5. volume": "5615561"}, "2020-03-03": {"1. open": "63.1400", "2. high": "66.1800", "3. low": "62.4300", "4. close": "64.2400", "5. volume": "5895674"}, "2020-03-02": {"1. open": "60.7700", "2. high": "62.6900", "3. low": "59.8300", "4. close": "62.6200", "5. volume": "4723395"}, "2020-02-28": {"1. open": "61.6000", "2. high": "61.7800", "3. low": "59.0200", "4. close": "60.3400", "5. volume": "4983312"}, "2020-02-27": {"1. open": "63.9300", "2. high": "65.4700", "3. low": "62.6900", "4. close": "62.9900", "5. volume": "3335670"}, "2020-02-26": {"1. open": "65.4700", "2. high": "66.8900", "3. low": "64.6627", "4. close": "64.8200", "5. volume": "3332905"}, "2020-02-25": {"1. open": "69.3400", "2. high": "69.3600", "3. low": "66.1800", "4. close": "66.4500", "5. volume": "2968168"}, "2020-02-24": {"1. open": "69.8100", "2. high": "70.3900", "3. low": "69.0700", "4. close": "69.1600", "5. volume": "2024281"}, "2020-02-21": {"1. open": "70.9300", "2. high": "71.3800", "3. low": "70.5200", "4. close": "70.6500", "5. volume": "1491684"}, "2020-02-20": {"1. open": "70.6100", "2. high": "71.2300", "3. low": "69.8800", "4. close": "71.0300", "5. volume": "1364329"}, "2020-02-19": {"1. open": "70.6800", "2. high": "70.9500", "3. low": "70.1800", "4. close": "70.4400", "5. volume": "1415973"}, "2020-02-18": {"1. open": "70.4600", "2. high": "71.1900", "3. low": "69.8600", "4. close": "70.1200", "5. volume": "2340595"}, "2020-02-14": {"1. open": "69.9200", "2. high": "70.5400", "3. low": "69.2200", "4. close": "70.3500", "5. volume": "1481703"}, "2020-02-13": {"1. open": "70.3000", "2. high": "70.4600", "3. low": "69.6500", "4. close": "69.7600", "5. volume": "2681058"}, "2020-02-12": {"1. open": "70.9200", "2. high": "70.9900", "3. low": "69.9000", "4. close": "70.3600", "5. volume": "3047178"}, "2020-02-11": {"1. open": "70.5700", "2. high": "71.2300", "3. low": "70.3900", "4. close": "71.2200", "5. volume": "2624027"}, "2020-02-10": {"1. open": "69.1100", "2. high": "70.2000", "3. low": "69.0900", "4. close": "70.0800", "5. volume": "2318321"}, "2020-02-07": {"1. open": "68.3000", "2. high": "69.4500", "3. low": "68.2600", "4. close": "68.9900", "5. volume": "2164294"}, "2020-02-06": {"1. open": "68.1200", "2. high": "68.6900", "3. low": "67.7400", "4. close": "68.1500", "5. volume": "2529073"}, "2020-02-05": {"1. open": "65.5600", "2. high": "68.0500", "3. low": "65.4400", "4. close": "67.9600", "5. volume": "2988409"}, "2020-02-04": {"1. open": "66.8700", "2. high": "67.0000", "3. low": "65.5700", "4. close": "65.6200", "5. volume": "2570905"}, "2020-02-03": {"1. open": "66.5100", "2. high": "67.1900", "3. low": "66.1450", "4. close": "66.6600", "5. volume": "2105714"}, "2020-01-31": {"1. open": "67.2600", "2. high": "67.6500", "3. low": "66.2500", "4. close": "66.3600", "5. volume": "2857230"}, "2020-01-30": {"1. open": "67.7500", "2. high": "68.1400", "3. low": "66.8100", "4. close": "67.2600", "5. volume": "2840341"}, "2020-01-29": {"1. open": "67.9500", "2. high": "68.2900", "3. low": "66.8200", "4. close": "67.7800", "5. volume": "2716919"}, "2020-01-28": {"1. open": "67.9400", "2. high": "68.5900", "3. low": "67.4000", "4. close": "67.7800", "5. volume": "4639938"}, "2020-01-27": {"1. open": "66.1700", "2. high": "67.7300", "3. low": "66.0000", "4. close": "67.2900", "5. volume": "3870521"}, "2020-01-24": {"1. open": "67.1900", "2. high": "68.0400", "3. low": "66.5600", "4. close": "66.6400", "5. volume": "5232856"}, "2020-01-23": {"1. open": "65.6900", "2. high": "67.8700", "3. low": "65.5300", "4. close": "67.2700", "5. volume": "5180787"}, "2020-01-22": {"1. open": "65.2500", "2. high": "66.2800", "3. low": "64.9400", "4. close": "65.7700", "5. volume": "3135009"}, "2020-01-21": {"1. open": "63.1500", "2. high": "65.0000", "3. low": "63.1500", "4. close": "64.9400", "5. volume": "3668529"}, "2020-01-17": {"1. open": "63.7800", "2. high": "64.0400", "3. low": "62.9800", "4. close": "63.0900", "5. volume": "3210729"}, "2020-01-16": {"1. open": "62.9500", "2. high": "63.3300", "3. low": "62.1700", "4. close": "63.1900", "5. volume": "2571901"}, "2020-01-15": {"1. open": "61.7500", "2. high": "63.0800", "3. low": "61.6300", "4. close": "62.7900", "5. volume": "3479940"}, "2020-01-14": {"1. open": "60.2500", "2. high": "61.6600", "3. low": "60.2500", "4. close": "61.6300", "5. volume": "3145507"}, "2020-01-13": {"1. open": "59.6300", "2. high": "60.6000", "3. low": "59.6300", "4. close": "60.5500", "5. volume": "4075685"}, "2020-01-10": {"1. open": "57.6900", "2. high": "59.8200", "3. low": "57.5100", "4. close": "59.7200", "5. volume": "5209240"}, "2020-01-09": {"1. open": "58.1200", "2. high": "59.1200", "3. low": "57.1600", "4. close": "57.6900", "5. volume": "5389838"}, "2020-01-08": {"1. open": "58.6800", "2. high": "60.2400", "3. low": "57.5650", "4. close": "57.5900", "5. volume": "9236663"}, "2020-01-07": {"1. open": "58.0900", "2. high": "58.3300", "3. low": "56.8000", "4. close": "57.1400", "5. volume": "5103647"}, "2020-01-06": {"1. open": "56.6800", "2. high": "58.3700", "3. low": "56.5400", "4. close": "58.0500", "5. volume": "6701715"}, "2020-01-03": {"1. open": "55.6400", "2. high": "56.7450", "3. low": "55.5000", "4. close": "56.4700", "5. volume": "2623634"}, "2020-01-02": {"1. open": "56.0700", "2. high": "56.1732", "3. low": "55.3100", "4. close": "55.8100", "5. volume": "3149218"}, "2019-12-31": {"1. open": "55.4700", "2. high": "56.0300", "3. low": "55.4350", "4. close": "55.7900", "5. volume": "2428170"}, "2019-12-30": {"1. open": "55.7500", "2. high": "55.9900", "3. low": "55.2100", "4. close": "55.7400", "5. volume": "5508131"}, "2019-12-27": {"1. open": "56.2800", "2. high": "56.3900", "3. low": "55.8800", "4. close": "56.0000", "5. volume": "3243152"}, "2019-12-26": {"1. open": "56.7000", "2. high": "56.9100", "3. low": "55.8700", "4. close": "56.0200", "5. volume": "2763240"}, "2019-12-24": {"1. open": "55.7500", "2. high": "56.8000", "3. low": "55.7500", "4. close": "56.7900", "5. volume": "1153704"}, "2019-12-23": {"1. open": "56.6400", "2. high": "56.8810", "3. low": "55.5300", "4. close": "55.6400", "5. volume": "2442384"}, "2019-12-20": {"1. open": "55.2200", "2. high": "56.7250", "3. low": "55.1400", "4. close": "56.6400", "5. volume": "5466700"}, "2019-12-19": {"1. open": "56.1400", "2. high": "56.4333", "3. low": "55.0950", "4. close": "55.2400", "5. volume": "4809216"}, "2019-12-18": {"1. open": "57.4600", "2. high": "57.4900", "3. low": "56.1500", "4. close": "56.2400", "5. volume": "4187044"}, "2019-12-17": {"1. open": "57.7500", "2. high": "58.0900", "3. low": "56.9200", "4. close": "57.2100", "5. volume": "3794634"}, "2019-12-16": {"1. open": "58.3100", "2. high": "58.6200", "3. low": "57.4400", "4. close": "58.1100", "5. volume": "2994456"}, "2019-12-13": {"1. open": "57.8300", "2. high": "58.6800", "3. low": "57.7300", "4. close": "58.3000", "5. volume": "3057697"}, "2019-12-12": {"1. open": "59.6600", "2. high": "59.8300", "3. low": "58.0400", "4. close": "58.0600", "5. volume": "2732138"}, "2019-12-11": {"1. open": "59.0600", "2. high": "59.7600", "3. low": "58.9600", "4. close": "59.7200", "5. volume": "1536246"}, "2019-12-10": {"1. open": "59.2200", "2. high": "59.4700", "3. low": "58.6300", "4. close": "59.1300", "5. volume": "1779174"}, "2019-12-09": {"1. open": "59.0200", "2. high": "59.7050", "3. low": "58.8500", "4. close": "59.4000", "5. volume": "2035494"}, "2019-12-06": {"1. open": "60.2300", "2. high": "60.2700", "3. low": "58.6400", "4. close": "58.7500", "5. volume": "2946139"}, "2019-12-05": {"1. open": "58.7700", "2. high": "59.9500", "3. low": "58.6400", "4. close": "59.8000", "5. volume": "2573055"}, "2019-12-04": {"1. open": "58.7900", "2. high": "59.3600", "3. low": "58.2800", "4. close": "58.8300", "5. volume": "3308681"}, "2019-12-03": {"1. open": "58.3600", "2. high": "58.9500", "3. low": "58.1100", "4. close": "58.9300", "5. volume": "2535600"}, "2019-12-02": {"1. open": "59.6000", "2. high": "59.6200", "3. low": "58.2900", "4. close": "58.8600", "5. volume": "1806830"}, "2019-11-29": {"1. open": "59.7800", "2. high": "60.0310", "3. low": "59.4725", "4. close": "59.6500", "5. volume": "1098705"}, "2019-11-27": {"1. open": "60.4100", "2. high": "60.6900", "3. low": "59.6500", "4. close": "59.7500", "5. volume": "2676703"}, "2019-11-26": {"1. open": "59.5100", "2. high": "60.4800", "3. low": "59.1800", "4. close": "60.4500", "5. volume": "2754827"}}}